MonoGen-0.3.4.dist-info/DESCRIPTION.rst
MonoGen-0.3.4.dist-info/METADATA
MonoGen-0.3.4.dist-info/RECORD
MonoGen-0.3.4.dist-info/WHEEL
MonoGen-0.3.4.dist-info/entry_points.txt
MonoGen-0.3.4.dist-info/metadata.json
MonoGen-0.3.4.dist-info/top_level.txt
monogen/__init__.py
monogen/accountcreator.py
monogen/console.py
monogen/gmailv.py
monogen/jibber.py
monogen/monoqueue.py
monogen/ptcexceptions.py
monogen/url.py
